satisfactory_save.cp312-win_amd64.pyd
satisfactory_save-0.9.0.dist-info/METADATA
satisfactory_save-0.9.0.dist-info/WHEEL
satisfactory_save-0.9.0.dist-info/licenses/LICENSE
satisfactory_save-0.9.0.dist-info/RECORD
