Metadata-Version: 2.2
Name: satisfactory-save
Version: 0.9.0
Summary: A savegame parsing package for Satisfactory.
Classifier: Development Status :: 3 - Alpha
Classifier: Intended Audience :: Developers
Classifier: License :: OSI Approved :: GNU General Public License v3 (GPLv3)
Classifier: Operating System :: Microsoft :: Windows
Classifier: Operating System :: POSIX :: Linux
Classifier: Programming Language :: C++
Classifier: Programming Language :: Python
Classifier: Programming Language :: Python :: 3
Classifier: Programming Language :: Python :: 3 :: Only
Classifier: Programming Language :: Python :: 3.9
Classifier: Programming Language :: Python :: 3.10
Classifier: Programming Language :: Python :: 3.11
Classifier: Programming Language :: Python :: 3.12
Classifier: Programming Language :: Python :: 3.13
Classifier: Topic :: File Formats
Classifier: Topic :: Games/Entertainment
Classifier: Topic :: Software Development
Project-URL: homepage, https://github.com/moritz-h/satisfactory-3d-map
Project-URL: source, https://github.com/moritz-h/satisfactory-3d-map
Project-URL: tracker, https://github.com/moritz-h/satisfactory-3d-map/issues
Requires-Python: >=3.9
